Metadata/__init__.py
Metadata/unique_sequences_pKJK5.csv
Modules/Phylogenetic.py
Modules/Prediction.py
Modules/__init__.py
plasmid_test3-0.1.data/scripts/plasmid_test
plasmid_test3-0.1.data/scripts/plasmid_test1
plasmid_test3-0.1.data/scripts/plasmid_test2
plasmid_test3-0.1.data/scripts/plasmid_test3
plasmid_test3-0.1.data/scripts/plasmidperm
plasmid_test3-0.1.data/scripts/plasmidpermm
plasmid_test3-0.1.data/scripts/plasmidpermmm
plasmid_test3-0.1.data/scripts/plasmidperx
plasmid_test3-0.1.data/scripts/plasmidperxx
plasmid_test3-0.1.data/scripts/plasmidperxxx
plasmid_test3-0.1.dist-info/LICENSE
plasmid_test3-0.1.dist-info/METADATA
plasmid_test3-0.1.dist-info/WHEEL
plasmid_test3-0.1.dist-info/top_level.txt
plasmid_test3-0.1.dist-info/RECORD
